{"data":[{"category":"MKM Magazine","link":"sites\/default\/files\/pdf\/mkm_january_2018_0.pdf","size":"5.33 mb","title":"Mkulima Mbunifu, No 65, Februari 2018"},
{"category":"MKM Magazine","link":"sites\/default\/files\/pdf\/mkm_january_2018.pdf","size":"5.33 mb","title":"Mkulima Mbunifu, No 64, Januari 2018"},
{"category":"MKM Magazine","link":"sites\/default\/files\/pdf\/mkm_december_2017.pdf","size":"3.28 mb","title":"Mkulima Mbunifu, No 63, Desemba 2017"},
{"category":"MKM Magazine","link":"sites\/default\/files\/pdf\/mkm_novemba_2017red.pdf","size":"1.85 mb","title":"Mkulima Mbunifu, No 62, Novemba 2017 "},
{"category":"MKM Magazine","link":"sites\/default\/files\/pdf\/mkm_october_2017red.pdf","size":"2.05 mb","title":"Mkulima Mbunifu, No 61, Oktoba 2017 "},
{"category":"MKM Magazine","link":"sites\/default\/files\/pdf\/mkm_september_2017red.pdf","size":"1.99 mb","title":"Mkulima Mbunifu, No 60, Septemba 2017 "},
{"category":"MKM Magazine","link":"sites\/default\/files\/pdf\/mkm_august_2017red.pdf","size":"1.37 mb","title":"Mkulima Mbunifu, No 59, Agosti 2017 "},
{"category":"MKM Magazine","link":"sites\/default\/files\/pdf\/mkm_july_2017red.pdf","size":"2.50 mb","title":"Mkulima Mbunifu, No 58, Julai 2017 "},
{"category":"MKM Magazine","link":"sites\/default\/files\/pdf\/mkm_june_2017_for_web.pdf","size":"1.03 mb","title":"Mkulima Mbunifu, No 57, Juni 2017 "},
{"category":"MKM Magazine","link":"sites\/default\/files\/pdf\/mkm_may_2017_for_web_0.pdf","size":"1.13 mb","title":"Mkulima Mbunifu, No 56, May 2017 "},
{"category":"MKM Magazine","link":"sites\/default\/files\/pdf\/mkm_aprili_2017_for_web_0.pdf","size":"896.20 kb","title":"Mkulima Mbunifu, No 55, Aprili 2017 "},
{"category":"MKM Magazine","link":"sites\/default\/files\/pdf\/mkm_machi_2017_for_web.pdf","size":"818.13 kb","title":"Mkulima Mbunifu, No 54, Machi 2017 "},
{"category":"MKM Magazine","link":"sites\/default\/files\/mkm_februari_2017_for_web.pdf","size":"823.82 kb","title":"Mkulima Mbunifu, No 53, Februari 2017 "},
{"category":"MKM Magazine","link":"sites\/default\/files\/mkm_januari_2017_for_web.pdf","size":"879.00 kb","title":"Mkulima Mbunifu, No 52, Januari 2017"},
{"category":"MKM Magazine","link":"sites\/default\/files\/mkm_disemba_2016_for_web.pdf","size":"772.68 kb","title":"Mkulima Mbunifu, No 51, Disemba 2016"},
{"category":"MKM Magazine","link":"sites\/default\/files\/mkm_novemba_2016_for_web.pdf","size":"888.20 kb","title":"Mkulima Mbunifu, No 50, Novemba 2016 "},
{"category":"MKM Magazine","link":"sites\/default\/files\/mkm_oktoba_2016_for_web.pdf","size":"766.19 kb","title":"Mkulima Mbunifu, No 49, Oktoba 2016 "},
{"category":"MKM Magazine","link":"sites\/default\/files\/mkm_septemba_2016_for_web.pdf","size":"868.32 kb","title":"Mkulima Mbunifu, No 48, Septemba 2016 "},
{"category":"MKM Magazine","link":"sites\/default\/files\/mkm_august_2016_for_web_0.pdf","size":"797.86 kb","title":"Mkulima Mbunifu, No 47, Agosti 2016 "},
{"category":"MKM Magazine","link":"sites\/default\/files\/mkm_julai_2016_for_web.pdf","size":"860.73 kb","title":"Mkulima Mbunifu, No 46, Julai 2016 "},
{"category":"MKM Magazine","link":"sites\/default\/files\/mkm_june_2016_for_web.pdf","size":"900.58 kb","title":"Mkulima Mbunifu, No 45, Juni 2016 "},
{"category":"MKM Magazine","link":"sites\/default\/files\/mkm_may_2016_for_web.pdf","size":"834.52 kb","title":"Mkulima Mbunifu, No 44, Mei 2016 "},
{"category":"MKM Magazine","link":"sites\/default\/files\/mkm_april_2016_for_web.pdf","size":"879.60 kb","title":"Mkulima Mbunifu, No 43, Aprili 2016"},
{"category":"MKM Magazine","link":"sites\/default\/files\/mkm_march_2016_for_web.pdf","size":"1.18 mb","title":"Mkulima Mbunifu, No 42, Machi 2016 "},
{"category":"MKM Magazine","link":"sites\/default\/files\/mkm_february_2016_for_web.pdf","size":"863.16 kb","title":"Mkulima Mbunifu, No 41, Februari 2016 "},
{"category":"MKM Magazine","link":"sites\/default\/files\/mkulima_mbunifu_jan_2016.pdf","size":"337.82 kb","title":"Mkulima Mbunifu, No 40, Januari 2016 "},
{"category":"MKM Magazine","link":"sites\/default\/files\/mkm_disemba_2015_for_web.pdf","size":"943.48 kb","title":"Mkulima Mbunifu, No 39, Disemba 2015 "},
{"category":"MKM Magazine","link":"sites\/default\/files\/mkm_novemba_2015_for_web.pdf","size":"873.33 kb","title":"Mkulima Mbunifu, No 38, Novemba 2015 "},
{"category":"MKM Magazine","link":"sites\/default\/files\/mkm_oktoba_2015_for_web.pdf","size":"947.35 kb","title":"Mkulima Mbunifu, No 37, Oktoba 2015"},
{"category":"MKM Magazine","link":"sites\/default\/files\/mkm_september_2015_for_web.pdf","size":"860.74 kb","title":"Mkulima Mbunifu, No 36, Septemba 2015"},
{"category":"MKM Magazine","link":"sites\/default\/files\/mkm_agosti_2015_for_web.pdf","size":"868.82 kb","title":"Mkulima Mbunifu, No 35, Agosti 2015"},
{"category":"MKM Magazine","link":"sites\/default\/files\/mkm_julai_2015_for_web.pdf","size":"3.43 mb","title":"Mkulima Mbunifu, No 34, Julai 2015"},
{"category":"MKM Magazine","link":"sites\/default\/files\/mkm_juni_2015.pdf","size":"3.48 mb","title":"Mkulima Mbunifu, No 33, Juni 2015 "},
{"category":"MKM Magazine","link":"sites\/default\/files\/mkm_mei_2015.pdf","size":"882.67 kb","title":"Mkulima Mbunifu, No 32, Mei 2015 "},
{"category":"MKM Magazine","link":"sites\/default\/files\/mkm_aprili_2015_for_web.pdf","size":"3.18 mb","title":"Mkulima Mbunifu, No 31, Aprili 2015 "},
{"category":"MKM Magazine","link":"sites\/default\/files\/mkm_machi_2015_for_web.pdf","size":"2.90 mb","title":"Mkulima Mbunifu, No 30, Machi 2015 "},
{"category":"MKM Magazine","link":"sites\/default\/files\/mkm_no._29_feb-2015.pdf","size":"2.92 mb","title":"Mkulima Mbunifu, No 29, Februari 2015 "},
{"category":"MKM Magazine","link":"sites\/default\/files\/mkm_no._28_jan-2015.pdf","size":"2.82 mb","title":"Mkulima Mbunifu, No 28, Januari 2015 "},
{"category":"MKM Magazine","link":"sites\/default\/files\/mkm_disemba_2014_for_web.pdf","size":"2.83 mb","title":"Mkulima Mbunifu, No 27, Disemba 2014 "},
{"category":"MKM Magazine","link":"sites\/default\/files\/4372.mkm_novemba_2014_for_web.pdf","size":"2.70 mb","title":"Mkulima Mbunifu, No 26, Novemba 2014"},
{"category":"MKM Magazine","link":"sites\/default\/files\/4371.mkm_no._25_oct_2014.pdf","size":"2.69 mb","title":"Mkulima Mbunifu, No 25, Oktoba 2014"},
{"category":"MKM Magazine","link":"sites\/default\/files\/4367.mkm_september_2014_prepress_new.pdf","size":"2.54 mb","title":"Mkulima Mbunifu, No 24, Septemba 2014"},
{"category":"MKM Magazine","link":"sites\/default\/files\/4361.mkm_no._23_aug_2014_0.pdf","size":"2.62 mb","title":"Mkulima Mbunifu, No 23, Agosti 2014"},
{"category":"MKM Magazine","link":"sites\/default\/files\/4358.mkm_julai_2014red.pdf","size":"2.26 mb","title":"Mkulima Mbunifu, No 22, Julai 2014"},
{"category":"MKM Magazine","link":"sites\/default\/files\/4347.mkm_june_2014red_0.pdf","size":"2.23 mb","title":"Mkulima Mbunifu, No 21, Juni 2014"},
{"category":"MKM Magazine","link":"sites\/default\/files\/4336.mkm_may_2014_for_web.pdf","size":"2.60 mb","title":"Mkulima Mbunifu, No 20, Mei 2014"},
{"category":"MKM Magazine","link":"sites\/default\/files\/4326.mkm_19_aprili_2014.pdf","size":"2.50 mb","title":"Mkulima Mbunifu, No 19, Aprili 2014"},
{"category":"MKM Magazine","link":"sites\/default\/files\/4319.mkm_machi_2014_for_web.pdf","size":"2.53 mb","title":"Mkulima Mbunifu, No 18, Machi 2014"},
{"category":"MKM Magazine","link":"sites\/default\/files\/4310.mkm_no_17_februari_2014red.pdf","size":"2.06 mb","title":"Mkulima Mbunifu, No 17, Februari 2014"},
{"category":"MKM Magazine","link":"sites\/default\/files\/4309.mkm_no_16_januari_2014red.pdf","size":"1.95 mb","title":"Mkulima Mbunifu, No 16, Januari 2014"},
{"category":"MKM Magazine","link":"sites\/default\/files\/4295.mkm_novemba_2013red.pdf","size":"2.47 mb","title":"Mkulima Mbunifu, No 15, Novemba 2013"},
{"category":"MKM Magazine","link":"sites\/default\/files\/4294.mkm_septemba_2013red.pdf","size":"1.93 mb","title":"Mkulima Mbunifu, No 14, Septemba 2013"},
{"category":"MKM Magazine","link":"sites\/default\/files\/4268.mkm_no.013_jul-2013red.pdf","size":"1.86 mb","title":"Mkulima Mbunifu, No 13, Julai 2013"},
{"category":"MKM Magazine","link":"sites\/default\/files\/4267.mkm_no._012_may-2013_0.pdf","size":"2.21 mb","title":"Mkulima Mbunifu, No 12, Mei 2013"},
{"category":"MKM Magazine","link":"sites\/default\/files\/4266.mkm_no._011_mac-2013.pdf","size":"2.12 mb","title":"Mkulima Mbunifu, No 11, Machi 2013"},
{"category":"MKM Magazine","link":"sites\/default\/files\/4176.mkulima_mbunifu_toleo_la_10red_0.pdf","size":"1.81 mb","title":"Mkulima Mbunifu, No 10, Januari 2013"},
{"category":"MKM Magazine","link":"sites\/default\/files\/4172.mkulima_mbunifu_toleo_la_9.pdf","size":"2.03 mb","title":"Mkulima Mbunifu, No 09, Novemba 2012"},
{"category":"MKM Magazine","link":"sites\/default\/files\/4171.mkulima_mbunifu_toleo_la_8.pdf","size":"2.12 mb","title":"Mkulima Mbunifu, No 08, Septemba 2012"},
{"category":"MKM Magazine","link":"sites\/default\/files\/4170.mkulima_mbunifu_toleo_la_7_0.pdf","size":"2.20 mb","title":"Mkulima Mbunifu, No 07, Julai 2012"},
{"category":"MKM Magazine","link":"sites\/default\/files\/4169.mkulima_mbunifu_toleo_la_6.pdf","size":"2.11 mb","title":"Mkulima Mbunifu, No 06, Mei 2012"},
{"category":"MKM Magazine","link":"sites\/default\/files\/4168.mkulima_mbunifu_toleo_la_5.pdf","size":"1.98 mb","title":"Mkulima Mbunifu, No 05, Machi 2012"},
{"category":"MKM Magazine","link":"sites\/default\/files\/4167.mkulima_mbunifu_toleo_la_4.pdf","size":"2.81 mb","title":"Mkulima Mbunifu, No 04, Januari 2012"},
{"category":"MKM Magazine","link":"sites\/default\/files\/4166.mkulima_mbunifu_toleo_la_3.pdf","size":"1.87 mb","title":"Mkulima Mbunifu, No 03, Novemba 2011"},
{"category":"MKM Magazine","link":"sites\/default\/files\/4165.mkulima_mbunifu_toleo_la_2.pdf","size":"1.91 mb","title":"Mkulima Mbunifu, No 02, Septemba 2011"},
{"category":"MKM Magazine","link":"sites\/default\/files\/3623.mkmbunifujulai2011.pdf","size":"2.00 mb","title":"Mkulima Mbunifu, No 01, Julai 2011"}]}